syncme.py
syncme-0.1.4.dist-info/METADATA
syncme-0.1.4.dist-info/RECORD
syncme-0.1.4.dist-info/WHEEL
syncme-0.1.4.dist-info/entry_points.txt
syncme-0.1.4.dist-info/top_level.txt
